bpy_meshbuilder-0.0.1.dist-info/licenses/LICENSE
meshbuilder/__init__.py
bpy_meshbuilder-0.0.1.dist-info/METADATA
bpy_meshbuilder-0.0.1.dist-info/WHEEL
bpy_meshbuilder-0.0.1.dist-info/top_level.txt
bpy_meshbuilder-0.0.1.dist-info/RECORD
